Youtiao-0.0.2.dist-info/METADATA
Youtiao-0.0.2.dist-info/RECORD
Youtiao-0.0.2.dist-info/WHEEL
Youtiao-0.0.2.dist-info/entry_points.txt
Youtiao-0.0.2.dist-info/top_level.txt
youtiao/__init__.py
youtiao/commands/__init__.py
youtiao/commands/docker.py
youtiao/commands/protoc.py
youtiao/commands/rancher.py
youtiao/commands/boilerplate/__init__.py
youtiao/commands/boilerplate/utils.py
youtiao/templates/__init__.py
youtiao/templates/py/__init__.py
youtiao/templates/py/grpc/.dockerignore.tpl
youtiao/templates/py/grpc/.gitignore.tpl
youtiao/templates/py/grpc/.gitlab-ci.yml.tpl
youtiao/templates/py/grpc/Dockerfile.tpl
youtiao/templates/py/grpc/requirements.txt.tpl
youtiao/templates/py/grpc/start.py.tpl
youtiao/templates/py/grpc/app/Grpc.py.tpl
youtiao/templates/py/grpc/app/__init__.py.tpl
youtiao/templates/py/grpc/app/api/__init__.py.tpl
youtiao/templates/py/grpc/app/api/grpc_sample_api.py.tpl
youtiao/templates/py/grpc/app/client/__init__.py.tpl
youtiao/templates/py/grpc/app/driver/Redis.py.tpl
youtiao/templates/py/grpc/app/driver/__init__.py.tpl
youtiao/templates/py/grpc/app/driver/mysql.py.tpl
youtiao/templates/py/grpc/app/driver/postgre.py.tpl
youtiao/templates/py/grpc/app/driver/sqlite.py.tpl
youtiao/templates/py/grpc/app/error/__init__.py.tpl
youtiao/templates/py/grpc/app/error/errors.json.tpl
youtiao/templates/py/grpc/app/model/__init__.py.tpl
youtiao/templates/py/grpc/app/module/__init__.py.tpl
youtiao/templates/py/grpc/app/proto/__init__.py.tpl
youtiao/templates/py/grpc/app/proto/app.proto.tpl
youtiao/templates/py/grpc/app/utils/__init__.py.tpl
youtiao/templates/py/grpc/app/utils/logger.py.tpl
youtiao/templates/py/grpc/app/utils/snowflake.py.tpl
youtiao/templates/py/grpc/config/default.yaml.tpl
youtiao/templates/py/grpc/scripts/health_check.py.tpl
youtiao/templates/py/http/.dockerignore.tpl
youtiao/templates/py/http/.gitignore.tpl
youtiao/templates/py/http/.gitlab-ci.yml.tpl
youtiao/templates/py/http/Dockerfile.tpl
youtiao/templates/py/http/requirements.txt.tpl
youtiao/templates/py/http/start.py.tpl
youtiao/templates/py/http/app/Http.py.tpl
youtiao/templates/py/http/app/__init__.py.tpl
