Metadata-Version: 2.1
Name: Youtiao
Version: 0.0.2
Summary: Micro Service Scaffold Generator and Toolkit
Home-page: https://github.com/Hujun/youtiao
Author: HJ
Author-email: hujun.qu@gmail.com
License: MIT
Platform: UNKNOWN
Classifier: Development Status :: 3 - Alpha
Classifier: Intended Audience :: Developers
Classifier: Topic :: Software Development :: Build Tools
Classifier: Topic :: Utilities
Classifier: License :: OSI Approved :: MIT License
Classifier: Programming Language :: Python :: 3.6
Requires-Python: >=3.6.0
Requires-Dist: click
Requires-Dist: colorama
Requires-Dist: jinja2
Requires-Dist: grpcio-tools
Requires-Dist: docker
Requires-Dist: requests
